e7_switcher/enums.py
e7_switcher/version.py
e7_switcher/client.py
e7_switcher/__init__.py
e7_switcher/_core.cpython-312-darwin.so
e7_switcher/cli.py
e7_switcher/.dylibs/libssl.3.dylib
e7_switcher/.dylibs/libcrypto.3.dylib
e7_switcher/.dylibs/libz.1.3.1.dylib
e7_switcher-1.0.8.dist-info/RECORD
e7_switcher-1.0.8.dist-info/WHEEL
e7_switcher-1.0.8.dist-info/entry_points.txt
e7_switcher-1.0.8.dist-info/METADATA
e7_switcher-1.0.8.dist-info/licenses/LICENSE
