Metadata-Version: 2.2
Name: e7-switcher
Version: 1.0.8
Summary: Python bindings for the e7-switcher C++ client
Author-Email: Elhanan Ilani <elhanan.ilani@gmail.com>
License: BSD 3-Clause License
Classifier: Programming Language :: Python :: 3
Classifier: Programming Language :: C++
Classifier: Operating System :: OS Independent
Project-URL: Homepage, https://github.com/elhanan7/e7-switcher
Requires-Python: >=3.8
